glycogym/__init__.py
glycogym/glycogym.py
glycogym-1.0.1.dist-info/METADATA
glycogym-1.0.1.dist-info/WHEEL
glycogym-1.0.1.dist-info/licenses/LICENSE
glycogym-1.0.1.dist-info/RECORD
