Metadata-Version: 2.4
Name: glycogym
Version: 1.0.1
Summary: A benchmark collection for glycan property prediction with tasks from variuos, glycobiologically relevant tasks.
License-File: LICENSE
Author: Roman Joeres
Author-email: roman.joeres@helmholtz-hips.de
Requires-Python: >=3.10
Classifier: Development Status :: 5 - Production/Stable
Classifier: License :: OSI Approved :: MIT License
Classifier: Operating System :: OS Independent
Classifier: Programming Language :: Python :: 3
Classifier: Programming Language :: Python :: 3.10
Classifier: Programming Language :: Python :: 3.11
Classifier: Programming Language :: Python :: 3.12
Classifier: Programming Language :: Python :: 3.13
Classifier: Programming Language :: Python :: 3.14
Requires-Dist: datasail (>=1.2.3)
Requires-Dist: glycowork
Requires-Dist: glyles (>=1.2.3a0)
Requires-Dist: numpy-indexed
Requires-Dist: nxontology
Requires-Dist: platformdirs
Project-URL: Repository, https://github.com/BojarLab/GlycoGym
